{
    "Title": "SEATED UPPER TRAPEZIUS STRETCH",
    "Directions": "The seated upper trapezius stretch aims to stretch out the neck. Begin by placing a hand on the opposite side of your head. Use your other hand to grip onto the bottom of your seat. Pull your head gently towards the side while rotating the head so that you are looking in the opposite direction. Hold the stretch for 20-30 seconds or as needed for relief.",
    "Muscles Involved": [
        "Upper Trapezius",
        "Splenius Cervicis",
        "Splenius Capitis"
    ],
    "Related Conditions": [
        "Cervicogenic Headaches",
        "Forward Head Posture",
        "Upper Cross Syndrome",
        "Text Neck / Nerd Neck",
        "Trapezius strain"
    ],
    "Video Link": "https:https://www.youtube.com/embed/TOioWuL4RxM?feature=oembed",
    "Image Link": "https://images.squarespace-cdn.com/content/v1/5f5e8592d2b0854b18af6975/f8af430a-7b2b-41f9-b386-bd828d3e5bcf/Levator+Scapulae+Stretch.jpg",
    "URL": "https://www.rehabhero.ca/exercise/seated-upper-trapezius-stretch",
    "Muscle group": [
        "Shoulder"
    ]
}